dbl_gateway/__init__.py
dbl_gateway/admission.py
dbl_gateway/app.py
dbl_gateway/auth.py
dbl_gateway/boundary.py
dbl_gateway/capabilities.py
dbl_gateway/config.py
dbl_gateway/context_builder.py
dbl_gateway/contracts.py
dbl_gateway/decision_builder.py
dbl_gateway/digest.py
dbl_gateway/event_builder.py
dbl_gateway/execution.py
dbl_gateway/governance.py
dbl_gateway/models.py
dbl_gateway/projection.py
dbl_gateway/ref_resolver.py
dbl_gateway/replay.py
dbl_gateway/wire_contract.py
dbl_gateway/adapters/__init__.py
dbl_gateway/adapters/execution_adapter_kl.py
dbl_gateway/adapters/policy_adapter_dbl_policy.py
dbl_gateway/adapters/store_adapter_sqlite.py
dbl_gateway/ports/__init__.py
dbl_gateway/ports/execution_port.py
dbl_gateway/ports/policy_port.py
dbl_gateway/ports/store_port.py
dbl_gateway/providers/__init__.py
dbl_gateway/providers/anthropic.py
dbl_gateway/providers/errors.py
dbl_gateway/providers/openai.py
dbl_gateway/store/__init__.py
dbl_gateway/store/base.py
dbl_gateway/store/factory.py
dbl_gateway/store/sqlite.py
deterministic_ai_gateway-0.4.0.dist-info/licenses/LICENSE
deterministic_ai_gateway-0.4.0.dist-info/METADATA
deterministic_ai_gateway-0.4.0.dist-info/WHEEL
deterministic_ai_gateway-0.4.0.dist-info/entry_points.txt
deterministic_ai_gateway-0.4.0.dist-info/top_level.txt
deterministic_ai_gateway-0.4.0.dist-info/RECORD
