Metadata-Version: 2.4
Name: deterministic-ai-gateway
Version: 0.4.0
Summary: Deterministic AI Gateway
License: MIT
Requires-Python: >=3.11
License-File: LICENSE
Requires-Dist: dbl-core<0.4.0,>=0.3.2
Requires-Dist: dbl-policy<0.3.0,>=0.2.0
Requires-Dist: dbl-main<0.4.0,>=0.3.0
Requires-Dist: dbl-ingress<0.2.0,>=0.1.1
Requires-Dist: kl-kernel-logic<0.6.0,>=0.5.0
Requires-Dist: fastapi>=0.110.0
Requires-Dist: uvicorn>=0.27.0
Requires-Dist: httpx>=0.27.0
Provides-Extra: dev
Requires-Dist: pytest<9,>=8; extra == "dev"
Requires-Dist: ruff<1,>=0.5; extra == "dev"
Requires-Dist: mypy<2,>=1.10; extra == "dev"
Requires-Dist: ensdg<0.5.0,>=0.4.0; extra == "dev"
Provides-Extra: oidc
Requires-Dist: python-jose[cryptography]<4,>=3.3; extra == "oidc"
Dynamic: license-file
